README.rst
setup.cfg
setup.py
mahokanta/__init__.py
mahokanta/app.py
mahokanta/server.py
mahokanta/tests.py
mahokanta.egg-info/PKG-INFO
mahokanta.egg-info/SOURCES.txt
mahokanta.egg-info/dependency_links.txt
mahokanta.egg-info/entry_points.txt
mahokanta.egg-info/requires.txt
mahokanta.egg-info/top_level.txt