Metadata-Version: 1.1
Name: mahokanta
Version: 0.0.2
Summary: A Web-Server to view HTTP-Request as raw text
Home-page: https://github.com/kjirou/python-mahokanta
Author: kjirou
Author-email: sorenariblog@gmail.com
License: MIT License
Keywords: http,tool,command
Platform: UNKNOWN
Classifier: Development Status :: 3 - Alpha
Classifier: Environment :: Console
Classifier: License :: OSI Approved :: MIT License
Classifier: Programming Language :: Python
Classifier: Programming Language :: Python :: 2.6
Classifier: Programming Language :: Python :: 2.7
Classifier: Programming Language :: Python :: 3
Classifier: Programming Language :: Python :: 3.2
Classifier: Programming Language :: Python :: 3.3
